<glosslist xmlns="http://docbook.org/ns/docbook" version="5.0">
  <title>Tasks</title>
  <glossentry>
    <glossterm>Task 1</glossterm>
    <glossdef>
      <formalpara>
        <title>Evaluate Cleanroom team performance and develop improvement 
        plans</title>
        <para>
          Evaluate project performance with respect to the 
          <citetitle>Software Development Plan</citetitle>, and apply trend 
          and causal analysis to deviations. 
        </para>
        <para>
          Apply causal analysis to faults found in the Correctness 
          Verification and the Statistical Testing and Certification 
          Processes to identify the steps in which they were introduced 
          and to determine why they occurred. 
        </para>
        <para>
          Compare process and product measurements with historical team 
          performance to assess process control.
        </para>
        <para>
          Develop plans to improve team perforamnce, including additional 
          training, improved tools and procedures, and revised Cleanroom 
          processes, and document the plans in the <citetitle>Performance 
          Improvement Plan</citetitle>.
        </para>
      </formalpara>
    </glossdef>
  </glossentry>
  <glossentry>
    <glossterm>Task 2</glossterm>
    <glossdef>
      <formalpara>
        <title>Evaluate new technolgoies and processess, and develop 
        implementation plans</title>
        <para>
          Identify new Cleanroom and other software technologies and 
          processes, and evaluate their impact on current Cleanroom processes. 
          Conduct experiments in the project environment to measure their 
          effectiveness.
        </para>
      </formalpara>
      <para>
        Develop plans for the introduction of proved new technologies and 
        processes, and document them in the <citetitle>Performance 
        Improvement Plan</citetitle> work product.
      </para>
      <para>
        Schedule new technology and process introductions for the start of 
        subsequent increments or subsequent projects as appropriate.
      </para>
    </glossdef>
  </glossentry>
</glosslist>
